searchallpdf.py
searchallpdf-0.2.0.dist-info/licenses/LICENSE
searchallpdf-0.2.0.dist-info/METADATA
searchallpdf-0.2.0.dist-info/WHEEL
searchallpdf-0.2.0.dist-info/entry_points.txt
searchallpdf-0.2.0.dist-info/top_level.txt
searchallpdf-0.2.0.dist-info/RECORD
