Metadata-Version: 2.4
Name: searchallpdf
Version: 0.2.0
Summary: Search for terms in all pdf in current and sub folders.
Author-email: Géry Casiez <gery.casiez@gmail.com>
License-Expression: MIT
Project-URL: Homepage, https://github.com/casiez/searchallpdf
Classifier: Programming Language :: Python :: 3
Requires-Python: >=3.0
License-File: LICENSE
Requires-Dist: argparse
Requires-Dist: pymupdf
Requires-Dist: pytesseract
Requires-Dist: pillow
Dynamic: license-file
